myocardial_mesh/MyocardialMesh.py
myocardial_mesh/__init__.py
myocardial_mesh/geometry_utils.py
myocardial_mesh-0.1.1.dist-info/licenses/LICENSE
myocardial_mesh-0.1.1.dist-info/METADATA
myocardial_mesh-0.1.1.dist-info/WHEEL
myocardial_mesh-0.1.1.dist-info/top_level.txt
myocardial_mesh-0.1.1.dist-info/RECORD
