Metadata-Version: 2.4
Name: myocardial-mesh
Version: 0.1.1
Summary: Ventricular myocardial mesh construction for ECG and FIM simulation
Author-email: Ricardo García Ramírez <rgr.5882@gmail.com>
License-Expression: MIT
Project-URL: Homepage, https://github.com/ricardogr07/purkinje-learning-myocardial-mesh
Project-URL: Repository, https://github.com/ricardogr07/purkinje-learning-myocardial-mesh
Keywords: mesh,myocardial,ECG,FIM,vtk,pyvista,simulation,biomedical
Requires-Python: >=3.8
License-File: LICENSE
Requires-Dist: numpy
Requires-Dist: scipy
Requires-Dist: vtk
Requires-Dist: pyvista
Requires-Dist: meshio
Requires-Dist: fim-python
Dynamic: license-file
